[
    {
        "%vlocity_namespace%__DomainObjectAPIName__c": "json",
        "%vlocity_namespace%__DomainObjectCreationOrder__c": 0,
        "%vlocity_namespace%__DomainObjectFieldAPIName__c": "DocumentLink",
        "%vlocity_namespace%__FilterGroup__c": 0,
        "%vlocity_namespace%__FilterOperator__c": "=",
        "%vlocity_namespace%__FilterValue__c": "objectId",
        "%vlocity_namespace%__GlobalKey__c": "3ce1ef09-dbaf-d9f8-4513-c93f6b15f2a7",
        "%vlocity_namespace%__InterfaceFieldAPIName__c": "%vlocity_namespace%__ObjectId__c",
        "%vlocity_namespace%__InterfaceObjectLookupOrder__c": 1,
        "%vlocity_namespace%__InterfaceObjectName__c": "%vlocity_namespace%__Document__c",
        "%vlocity_namespace%__IsDisabled__c": false,
        "%vlocity_namespace%__IsRequiredForUpsert__c": false,
        "%vlocity_namespace%__MapId__c": "GenericDocuSignGetDocumentsCustom7291",
        "%vlocity_namespace%__UpsertKey__c": false,
        "Name": "GenericDocuSignGetDocuments",
        "VlocityDataPackType": "SObject",
        "VlocityRecordSObjectType": "%vlocity_namespace%__DRMapItem__c"
    },
    {
        "%vlocity_namespace%__DomainObjectAPIName__c": "json",
        "%vlocity_namespace%__DomainObjectCreationOrder__c": 0,
        "%vlocity_namespace%__DomainObjectFieldAPIName__c": "ContentVersions",
        "%vlocity_namespace%__FilterGroup__c": 0,
        "%vlocity_namespace%__FilterOperator__c": "=",
        "%vlocity_namespace%__FilterValue__c": "DocumentLink:%vlocity_namespace%__DocumentSourceId__c",
        "%vlocity_namespace%__GlobalKey__c": "f8dfaa7e-7273-1feb-880c-ffdc1b507cd1",
        "%vlocity_namespace%__InterfaceFieldAPIName__c": "Id",
        "%vlocity_namespace%__InterfaceObjectLookupOrder__c": 2,
        "%vlocity_namespace%__InterfaceObjectName__c": "ContentVersion",
        "%vlocity_namespace%__IsDisabled__c": false,
        "%vlocity_namespace%__IsRequiredForUpsert__c": false,
        "%vlocity_namespace%__MapId__c": "GenericDocuSignGetDocumentsCustom1798",
        "%vlocity_namespace%__UpsertKey__c": false,
        "Name": "GenericDocuSignGetDocuments",
        "VlocityDataPackType": "SObject",
        "VlocityRecordSObjectType": "%vlocity_namespace%__DRMapItem__c"
    },
    {
        "%vlocity_namespace%__DomainObjectAPIName__c": "json",
        "%vlocity_namespace%__DomainObjectCreationOrder__c": 0,
        "%vlocity_namespace%__DomainObjectFieldAPIName__c": "Attachments",
        "%vlocity_namespace%__FilterGroup__c": 0,
        "%vlocity_namespace%__FilterOperator__c": "=",
        "%vlocity_namespace%__FilterValue__c": "DocumentLink:%vlocity_namespace%__DocumentSourceId__c",
        "%vlocity_namespace%__GlobalKey__c": "3213a6aa-806a-0429-0fbb-a517f17393e3",
        "%vlocity_namespace%__InterfaceFieldAPIName__c": "Id",
        "%vlocity_namespace%__InterfaceObjectLookupOrder__c": 3,
        "%vlocity_namespace%__InterfaceObjectName__c": "Attachment",
        "%vlocity_namespace%__IsDisabled__c": false,
        "%vlocity_namespace%__IsRequiredForUpsert__c": false,
        "%vlocity_namespace%__MapId__c": "GenericDocuSignGetDocumentsCustom9016",
        "%vlocity_namespace%__UpsertKey__c": false,
        "Name": "GenericDocuSignGetDocuments",
        "VlocityDataPackType": "SObject",
        "VlocityRecordSObjectType": "%vlocity_namespace%__DRMapItem__c"
    },
    {
        "%vlocity_namespace%__DomainObjectAPIName__c": "json",
        "%vlocity_namespace%__DomainObjectCreationOrder__c": 0,
        "%vlocity_namespace%__DomainObjectFieldAPIName__c": "ManualUploads",
        "%vlocity_namespace%__FilterGroup__c": 0,
        "%vlocity_namespace%__FilterOperator__c": "=",
        "%vlocity_namespace%__FilterValue__c": "objectId",
        "%vlocity_namespace%__GlobalKey__c": "34753407-7530-cffd-0e84-427ca971a4ac",
        "%vlocity_namespace%__InterfaceFieldAPIName__c": "FirstPublishLocationId",
        "%vlocity_namespace%__InterfaceObjectLookupOrder__c": 4,
        "%vlocity_namespace%__InterfaceObjectName__c": "ContentVersion",
        "%vlocity_namespace%__IsDisabled__c": false,
        "%vlocity_namespace%__IsRequiredForUpsert__c": false,
        "%vlocity_namespace%__MapId__c": "GenericDocuSignGetDocumentsCustom6410",
        "%vlocity_namespace%__UpsertKey__c": false,
        "Name": "GenericDocuSignGetDocuments",
        "VlocityDataPackType": "SObject",
        "VlocityRecordSObjectType": "%vlocity_namespace%__DRMapItem__c"
    },
    {
        "%vlocity_namespace%__DomainObjectAPIName__c": "json",
        "%vlocity_namespace%__DomainObjectCreationOrder__c": 0,
        "%vlocity_namespace%__DomainObjectFieldAPIName__c": "ManualUploads",
        "%vlocity_namespace%__FilterGroup__c": 0,
        "%vlocity_namespace%__FilterOperator__c": "NOT LIKE",
        "%vlocity_namespace%__FilterValue__c": "\"signed_%\"",
        "%vlocity_namespace%__GlobalKey__c": "75bdb1dc-8aec-27df-9ca8-63bc3bb50f6b",
        "%vlocity_namespace%__InterfaceFieldAPIName__c": "Title",
        "%vlocity_namespace%__InterfaceObjectLookupOrder__c": 4,
        "%vlocity_namespace%__InterfaceObjectName__c": "ContentVersion",
        "%vlocity_namespace%__IsDisabled__c": false,
        "%vlocity_namespace%__IsRequiredForUpsert__c": false,
        "%vlocity_namespace%__MapId__c": "GenericDocuSignGetDocumentsCustom3357",
        "%vlocity_namespace%__UpsertKey__c": false,
        "Name": "GenericDocuSignGetDocuments",
        "VlocityDataPackType": "SObject",
        "VlocityRecordSObjectType": "%vlocity_namespace%__DRMapItem__c"
    },
    {
        "%vlocity_namespace%__DomainObjectAPIName__c": "Formula",
        "%vlocity_namespace%__DomainObjectCreationOrder__c": 0,
        "%vlocity_namespace%__DomainObjectFieldAPIName__c": "Formula",
        "%vlocity_namespace%__FormulaOrder__c": 1,
        "%vlocity_namespace%__FormulaResultPath__c": "ContentVersions:FileExtension",
        "%vlocity_namespace%__Formula__c": "IF (ContentVersions:FileExtension == \"pdf\", \"pdf\", IF (ContentVersions:FileExtension == \"docx\", \"docx\", null))",
        "%vlocity_namespace%__GlobalKey__c": "e381754c-cbe0-e66f-9dc5-6b50a59eb5e0",
        "%vlocity_namespace%__IsDisabled__c": true,
        "%vlocity_namespace%__IsRequiredForUpsert__c": false,
        "%vlocity_namespace%__MapId__c": "GenericDocuSignGetDocuments4186190854798093",
        "%vlocity_namespace%__UpsertKey__c": false,
        "Name": "GenericDocuSignGetDocuments",
        "VlocityDataPackType": "SObject",
        "VlocityRecordSObjectType": "%vlocity_namespace%__DRMapItem__c"
    },
    {
        "%vlocity_namespace%__DomainObjectAPIName__c": "Formula",
        "%vlocity_namespace%__DomainObjectCreationOrder__c": 0,
        "%vlocity_namespace%__DomainObjectFieldAPIName__c": "Formula",
        "%vlocity_namespace%__FormulaOrder__c": 2,
        "%vlocity_namespace%__FormulaResultPath__c": "Attachments:FileExtension",
        "%vlocity_namespace%__Formula__c": "IF (Attachments:ContentType == \"application/pdf\", \"pdf\", IF (Attachments:ContentType == \"application/vnd.openxmlformats-officedocument.wordprocessingml.document\", \"docx\", null))",
        "%vlocity_namespace%__GlobalKey__c": "106e1777-8c8d-c428-041a-6d2c76a135ea",
        "%vlocity_namespace%__IsDisabled__c": false,
        "%vlocity_namespace%__IsRequiredForUpsert__c": false,
        "%vlocity_namespace%__MapId__c": "GenericDocuSignGetDocumentsCustom9522",
        "%vlocity_namespace%__UpsertKey__c": false,
        "Name": "GenericDocuSignGetDocuments",
        "VlocityDataPackType": "SObject",
        "VlocityRecordSObjectType": "%vlocity_namespace%__DRMapItem__c"
    },
    {
        "%vlocity_namespace%__DomainObjectAPIName__c": "Formula",
        "%vlocity_namespace%__DomainObjectCreationOrder__c": 0,
        "%vlocity_namespace%__DomainObjectFieldAPIName__c": "Formula",
        "%vlocity_namespace%__FormulaOrder__c": 3,
        "%vlocity_namespace%__FormulaResultPath__c": "Attachments:SourceType",
        "%vlocity_namespace%__Formula__c": "IF(Attachments:Id,\"Attachment\", null)",
        "%vlocity_namespace%__GlobalKey__c": "00eca509-1070-6086-d813-2c217b8ca0ee",
        "%vlocity_namespace%__IsDisabled__c": false,
        "%vlocity_namespace%__IsRequiredForUpsert__c": false,
        "%vlocity_namespace%__MapId__c": "GenericDocuSignGetDocumentsCustom9830",
        "%vlocity_namespace%__UpsertKey__c": false,
        "Name": "GenericDocuSignGetDocuments",
        "VlocityDataPackType": "SObject",
        "VlocityRecordSObjectType": "%vlocity_namespace%__DRMapItem__c"
    },
    {
        "%vlocity_namespace%__DomainObjectAPIName__c": "Formula",
        "%vlocity_namespace%__DomainObjectCreationOrder__c": 0,
        "%vlocity_namespace%__DomainObjectFieldAPIName__c": "Formula",
        "%vlocity_namespace%__FormulaOrder__c": 4,
        "%vlocity_namespace%__FormulaResultPath__c": "ContentVersions:SourceType",
        "%vlocity_namespace%__Formula__c": "IF(ContentVersions:Id, \"Content\", null)",
        "%vlocity_namespace%__GlobalKey__c": "5080d001-21f3-74df-d7b3-7afdedd84823",
        "%vlocity_namespace%__IsDisabled__c": false,
        "%vlocity_namespace%__IsRequiredForUpsert__c": false,
        "%vlocity_namespace%__MapId__c": "GenericDocuSignGetDocumentsCustom8945",
        "%vlocity_namespace%__UpsertKey__c": false,
        "Name": "GenericDocuSignGetDocuments",
        "VlocityDataPackType": "SObject",
        "VlocityRecordSObjectType": "%vlocity_namespace%__DRMapItem__c"
    },
    {
        "%vlocity_namespace%__DomainObjectAPIName__c": "Formula",
        "%vlocity_namespace%__DomainObjectCreationOrder__c": 0,
        "%vlocity_namespace%__DomainObjectFieldAPIName__c": "Formula",
        "%vlocity_namespace%__FormulaOrder__c": 5,
        "%vlocity_namespace%__FormulaResultPath__c": "ManualUploads:SourceType",
        "%vlocity_namespace%__Formula__c": "IF(ManualUploads:Id, \"Content\", null)",
        "%vlocity_namespace%__GlobalKey__c": "928c8da5-78f2-75ae-153f-fb7669947c4a",
        "%vlocity_namespace%__IsDisabled__c": false,
        "%vlocity_namespace%__IsRequiredForUpsert__c": false,
        "%vlocity_namespace%__MapId__c": "GenericDocuSignGetDocumentsCustom4245",
        "%vlocity_namespace%__UpsertKey__c": false,
        "Name": "GenericDocuSignGetDocuments",
        "VlocityDataPackType": "SObject",
        "VlocityRecordSObjectType": "%vlocity_namespace%__DRMapItem__c"
    },
    {
        "%vlocity_namespace%__DomainObjectAPIName__c": "Formula",
        "%vlocity_namespace%__DomainObjectCreationOrder__c": 0,
        "%vlocity_namespace%__DomainObjectFieldAPIName__c": "Formula",
        "%vlocity_namespace%__FormulaOrder__c": 6,
        "%vlocity_namespace%__FormulaResultPath__c": "Documents",
        "%vlocity_namespace%__Formula__c": "SORTBY(LIST(Attachments, ContentVersions, ManualUploads), 'CreatedDate:DSC')",
        "%vlocity_namespace%__GlobalKey__c": "26f74890-32dc-7b2f-7f46-9d97a0b4803a",
        "%vlocity_namespace%__IsDisabled__c": false,
        "%vlocity_namespace%__IsRequiredForUpsert__c": false,
        "%vlocity_namespace%__MapId__c": "GenericDocuSignGetDocumentsCustom9733",
        "%vlocity_namespace%__UpsertKey__c": false,
        "Name": "GenericDocuSignGetDocuments",
        "VlocityDataPackType": "SObject",
        "VlocityRecordSObjectType": "%vlocity_namespace%__DRMapItem__c"
    },
    {
        "%vlocity_namespace%__DomainObjectAPIName__c": "json",
        "%vlocity_namespace%__DomainObjectCreationOrder__c": 1,
        "%vlocity_namespace%__DomainObjectFieldAPIName__c": "documents:fileExtension",
        "%vlocity_namespace%__GlobalKey__c": "dde06d2c-4636-57b0-5e3d-0059ad67ea15",
        "%vlocity_namespace%__InterfaceFieldAPIName__c": "Documents:FileExtension",
        "%vlocity_namespace%__IsDisabled__c": false,
        "%vlocity_namespace%__IsRequiredForUpsert__c": false,
        "%vlocity_namespace%__MapId__c": "GenericDocuSignGetDocumentsCustom736",
        "%vlocity_namespace%__UpsertKey__c": false,
        "Name": "GenericDocuSignGetDocuments",
        "VlocityDataPackType": "SObject",
        "VlocityRecordSObjectType": "%vlocity_namespace%__DRMapItem__c"
    },
    {
        "%vlocity_namespace%__DomainObjectAPIName__c": "json",
        "%vlocity_namespace%__DomainObjectCreationOrder__c": 1,
        "%vlocity_namespace%__DomainObjectFieldAPIName__c": "documents:id",
        "%vlocity_namespace%__GlobalKey__c": "024f6d71-528f-60d2-5072-45261ee4bf7b",
        "%vlocity_namespace%__InterfaceFieldAPIName__c": "Documents:Id",
        "%vlocity_namespace%__IsDisabled__c": false,
        "%vlocity_namespace%__IsRequiredForUpsert__c": false,
        "%vlocity_namespace%__MapId__c": "GenericDocuSignGetDocumentsCustom2263",
        "%vlocity_namespace%__UpsertKey__c": false,
        "Name": "GenericDocuSignGetDocuments",
        "VlocityDataPackType": "SObject",
        "VlocityRecordSObjectType": "%vlocity_namespace%__DRMapItem__c"
    },
    {
        "%vlocity_namespace%__DomainObjectAPIName__c": "json",
        "%vlocity_namespace%__DomainObjectCreationOrder__c": 1,
        "%vlocity_namespace%__DomainObjectFieldAPIName__c": "documents:name",
        "%vlocity_namespace%__GlobalKey__c": "1fe02c57-27c0-e6c4-0475-dcfb5fabbaa3",
        "%vlocity_namespace%__InterfaceFieldAPIName__c": "Documents:Name",
        "%vlocity_namespace%__IsDisabled__c": false,
        "%vlocity_namespace%__IsRequiredForUpsert__c": false,
        "%vlocity_namespace%__MapId__c": "GenericDocuSignGetDocumentsCustom8552",
        "%vlocity_namespace%__UpsertKey__c": false,
        "Name": "GenericDocuSignGetDocuments",
        "VlocityDataPackType": "SObject",
        "VlocityRecordSObjectType": "%vlocity_namespace%__DRMapItem__c"
    },
    {
        "%vlocity_namespace%__DomainObjectAPIName__c": "json",
        "%vlocity_namespace%__DomainObjectCreationOrder__c": 1,
        "%vlocity_namespace%__DomainObjectFieldAPIName__c": "documents:name",
        "%vlocity_namespace%__GlobalKey__c": "ea37f199-fba9-d953-d240-937a4b265c75",
        "%vlocity_namespace%__InterfaceFieldAPIName__c": "Documents:Title",
        "%vlocity_namespace%__IsDisabled__c": false,
        "%vlocity_namespace%__IsRequiredForUpsert__c": false,
        "%vlocity_namespace%__MapId__c": "GenericDocuSignGetDocumentsCustom7115",
        "%vlocity_namespace%__UpsertKey__c": false,
        "Name": "GenericDocuSignGetDocuments",
        "VlocityDataPackType": "SObject",
        "VlocityRecordSObjectType": "%vlocity_namespace%__DRMapItem__c"
    },
    {
        "%vlocity_namespace%__DomainObjectAPIName__c": "json",
        "%vlocity_namespace%__DomainObjectCreationOrder__c": 1,
        "%vlocity_namespace%__DomainObjectFieldAPIName__c": "documents:sourceId",
        "%vlocity_namespace%__GlobalKey__c": "2d697ceb-43ca-c49c-5350-1444881bfccf",
        "%vlocity_namespace%__InterfaceFieldAPIName__c": "Documents:Id",
        "%vlocity_namespace%__IsDisabled__c": false,
        "%vlocity_namespace%__IsRequiredForUpsert__c": false,
        "%vlocity_namespace%__MapId__c": "GenericDocuSignGetDocumentsCustom7579",
        "%vlocity_namespace%__UpsertKey__c": false,
        "Name": "GenericDocuSignGetDocuments",
        "VlocityDataPackType": "SObject",
        "VlocityRecordSObjectType": "%vlocity_namespace%__DRMapItem__c"
    },
    {
        "%vlocity_namespace%__DomainObjectAPIName__c": "json",
        "%vlocity_namespace%__DomainObjectCreationOrder__c": 1,
        "%vlocity_namespace%__DomainObjectFieldAPIName__c": "documents:sourceType",
        "%vlocity_namespace%__GlobalKey__c": "1693894f-c7a1-425a-1d6d-9d15f0b583eb",
        "%vlocity_namespace%__InterfaceFieldAPIName__c": "Documents:SourceType",
        "%vlocity_namespace%__IsDisabled__c": false,
        "%vlocity_namespace%__IsRequiredForUpsert__c": false,
        "%vlocity_namespace%__MapId__c": "GenericDocuSignGetDocumentsCustom7672",
        "%vlocity_namespace%__UpsertKey__c": false,
        "Name": "GenericDocuSignGetDocuments",
        "VlocityDataPackType": "SObject",
        "VlocityRecordSObjectType": "%vlocity_namespace%__DRMapItem__c"
    }
]